{
	"name": "ls_onprem_sql_",
	"properties": {
		"annotations": [],
		"type": "SqlServer",
		"typeProperties": {
			"server": "YASH",
			"database": "tpcxbb_1gb",
			"encrypt": "mandatory",
			"trustServerCertificate": true,
			"authenticationType": "SQL",
			"userName": "Nataraj",
			"password": {
				"type": "AzureKeyVaultSecret",
				"store": {
					"referenceName": "ls_keyvault",
					"type": "LinkedServiceReference"
				},
				"secretName": "sqlDbpassword"
			}
		},
		"connectVia": {
			"referenceName": "onpremintegrationRuntime1",
			"type": "IntegrationRuntimeReference"
		}
	},
	"type": "Microsoft.DataFactory/factories/linkedservices"
}